sarer/__init__.py
sarer-0.1.dist-info/LICENSE.txt
sarer-0.1.dist-info/METADATA
sarer-0.1.dist-info/WHEEL
sarer-0.1.dist-info/top_level.txt
sarer-0.1.dist-info/RECORD
