Metadata-Version: 2.1
Name: sarer
Version: 0.1
Summary: i do not tell you
Author: sarer
Author-email: niveco1990@bizatop.com
Classifier: Programming Language :: Python :: 3
Classifier: License :: OSI Approved :: MIT License
Classifier: Operating System :: OS Independent
License-File: LICENSE.txt
